function.py
pyspigot.py
dev/magicmq/pyspigot/PlatformAdapter.py
dev/magicmq/pyspigot/PluginListener.py
dev/magicmq/pyspigot/PyCore.py
dev/magicmq/pyspigot/__init__.py
dev/magicmq/pyspigot/bukkit/BukkitListener.py
dev/magicmq/pyspigot/bukkit/PySpigot.py
dev/magicmq/pyspigot/bukkit/__init__.py
dev/magicmq/pyspigot/bukkit/command/BukkitPluginCommand.py
dev/magicmq/pyspigot/bukkit/command/__init__.py
dev/magicmq/pyspigot/bukkit/config/BukkitPluginConfig.py
dev/magicmq/pyspigot/bukkit/config/__init__.py
dev/magicmq/pyspigot/bukkit/event/ScriptEvent.py
dev/magicmq/pyspigot/bukkit/event/ScriptExceptionEvent.py
dev/magicmq/pyspigot/bukkit/event/ScriptLoadEvent.py
dev/magicmq/pyspigot/bukkit/event/ScriptUnloadEvent.py
dev/magicmq/pyspigot/bukkit/event/__init__.py
dev/magicmq/pyspigot/bukkit/event/custom/CustomEvent.py
dev/magicmq/pyspigot/bukkit/event/custom/__init__.py
dev/magicmq/pyspigot/bukkit/manager/command/BukkitCommandManager.py
dev/magicmq/pyspigot/bukkit/manager/command/BukkitScriptCommand.py
dev/magicmq/pyspigot/bukkit/manager/command/__init__.py
dev/magicmq/pyspigot/bukkit/manager/config/BukkitConfigManager.py
dev/magicmq/pyspigot/bukkit/manager/config/BukkitScriptConfig.py
dev/magicmq/pyspigot/bukkit/manager/config/__init__.py
dev/magicmq/pyspigot/bukkit/manager/listener/BukkitListenerManager.py
dev/magicmq/pyspigot/bukkit/manager/listener/BukkitScriptEventExecutor.py
dev/magicmq/pyspigot/bukkit/manager/listener/BukkitScriptEventListener.py
dev/magicmq/pyspigot/bukkit/manager/listener/__init__.py
dev/magicmq/pyspigot/bukkit/manager/placeholder/PlaceholderManager.py
dev/magicmq/pyspigot/bukkit/manager/placeholder/ScriptPlaceholder.py
dev/magicmq/pyspigot/bukkit/manager/placeholder/__init__.py
dev/magicmq/pyspigot/bukkit/manager/protocol/AsyncProtocolManager.py
dev/magicmq/pyspigot/bukkit/manager/protocol/ListenerType.py
dev/magicmq/pyspigot/bukkit/manager/protocol/PacketReceivingListener.py
dev/magicmq/pyspigot/bukkit/manager/protocol/PacketSendingListener.py
pyspigot_sources-0.8.0.dist-info/LICENSE
pyspigot_sources-0.8.0.dist-info/METADATA
pyspigot_sources-0.8.0.dist-info/WHEEL
pyspigot_sources-0.8.0.dist-info/top_level.txt
pyspigot_sources-0.8.0.dist-info/RECORD
